{"trial_id": "0070", "hyperparameters": {"space": [{"class_name": "Int", "config": {"name": "num_dense_d1", "default": null, "conditions": [], "min_value": 1, "max_value": 9, "step": 1, "sampling": null}}, {"class_name": "Int", "config": {"name": "dense_d1_0", "default": null, "conditions": [], "min_value": 4, "max_value": 64, "step": 2, "sampling": null}}, {"class_name": "Int", "config": {"name": "num_dense_li", "default": null, "conditions": [], "min_value": 1, "max_value": 4, "step": 1, "sampling": null}}, {"class_name": "Int", "config": {"name": "dense_d1_1", "default": null, "conditions": [], "min_value": 4, "max_value": 64, "step": 2, "sampling": null}}, {"class_name": "Int", "config": {"name": "dense_d1_2", "default": null, "conditions": [], "min_value": 4, "max_value": 64, "step": 2, "sampling": null}}, {"class_name": "Int", "config": {"name": "dense_d1_3", "default": null, "conditions": [], "min_value": 4, "max_value": 64, "step": 2, "sampling": null}}, {"class_name": "Int", "config": {"name": "dense_d1_4", "default": null, "conditions": [], "min_value": 4, "max_value": 64, "step": 2, "sampling": null}}, {"class_name": "Int", "config": {"name": "dense_d1_5", "default": null, "conditions": [], "min_value": 4, "max_value": 64, "step": 2, "sampling": null}}, {"class_name": "Boolean", "config": {"name": "shuffle", "default": false, "conditions": []}}, {"class_name": "Int", "config": {"name": "dense_d1_6", "default": null, "conditions": [], "min_value": 4, "max_value": 64, "step": 2, "sampling": null}}, {"class_name": "Int", "config": {"name": "dense_d1_7", "default": null, "conditions": [], "min_value": 4, "max_value": 64, "step": 2, "sampling": null}}, {"class_name": "Int", "config": {"name": "dense_d1_8", "default": null, "conditions": [], "min_value": 4, "max_value": 64, "step": 2, "sampling": null}}], "values": {"num_dense_d1": 3, "dense_d1_0": 58, "num_dense_li": 1, "dense_d1_1": 20, "dense_d1_2": 24, "dense_d1_3": 32, "dense_d1_4": 34, "dense_d1_5": 40, "shuffle": false, "dense_d1_6": 44, "dense_d1_7": 26, "dense_d1_8": 46, "tuner/epochs": 17, "tuner/initial_epoch": 6, "tuner/bracket": 2, "tuner/round": 1, "tuner/trial_id": "0061"}}, "metrics": {"metrics": {"loss": {"direction": "min", "observations": [{"value": [0.05989406257867813], "step": 10}]}, "mean_absolute_error": {"direction": "min", "observations": [{"value": [0.2039886862039566], "step": 10}]}, "val_loss": {"direction": "min", "observations": [{"value": [0.06275030225515366], "step": 10}]}, "val_mean_absolute_error": {"direction": "min", "observations": [{"value": [0.20690415799617767], "step": 10}]}}}, "score": 0.06275030225515366, "best_step": 10, "status": "COMPLETED"}